dpdtrack/__init__.py
dpdtrack/classes/__init__.py
dpdtrack/classes/api.py
dpdtrack/classes/http.py
dpdtrack/classes/shipment.py
dpdtrack-0.10.0.dist-info/METADATA
dpdtrack-0.10.0.dist-info/WHEEL
dpdtrack-0.10.0.dist-info/licenses/LICENSE
dpdtrack-0.10.0.dist-info/RECORD
