Metadata-Version: 2.1
Name: dpdtrack
Version: 0.10.0
Summary: Simple Python wrapper to fetch data from DPD Austria (mydpd.at) and Romania (dpd.ro)
Project-URL: Homepage, https://kumig.it/kumitterer/dpdtrack
Project-URL: Bug Tracker, https://kumig.it/kumitterer/dpdtrack/issues
Author-email: Kumi Mitterer <dpdtrack@kumi.email>
License: Copyright (c) 2023 Kumi Mitterer <dpdtrack@kumi.email>
License-File: LICENSE
Classifier: License :: OSI Approved :: MIT License
Classifier: Operating System :: OS Independent
Classifier: Programming Language :: Python :: 3
Requires-Python: >=3.10
Requires-Dist: beautifulsoup4
